setup.py
cqparts_bearings/LICENSE
cqparts_bearings/__init__.py
cqparts_bearings/ball.py
cqparts_bearings/tapered_roller.py
cqparts_bearings.egg-info/PKG-INFO
cqparts_bearings.egg-info/SOURCES.txt
cqparts_bearings.egg-info/dependency_links.txt
cqparts_bearings.egg-info/not-zip-safe
cqparts_bearings.egg-info/requires.txt
cqparts_bearings.egg-info/top_level.txt